splitter_client_fds/__init__.py
splitter_client_fds/cli.py
splitter_client_fds/backend/main.py
splitter_client_fds/backend/requirements.txt
splitter_client_fds/backend/node_modules/.package-lock.json
splitter_client_fds/backend/node_modules/.bin/loose-envify
splitter_client_fds/backend/node_modules/@fontsource/sora/100.css
splitter_client_fds/backend/node_modules/@fontsource/sora/200.css
splitter_client_fds/backend/node_modules/@fontsource/sora/300.css
splitter_client_fds/backend/node_modules/@fontsource/sora/400.css
splitter_client_fds/backend/node_modules/@fontsource/sora/500.css
splitter_client_fds/backend/node_modules/@fontsource/sora/600.css
splitter_client_fds/backend/node_modules/@fontsource/sora/700.css
splitter_client_fds/backend/node_modules/@fontsource/sora/800.css
splitter_client_fds/backend/node_modules/@fontsource/sora/CHANGELOG.md
splitter_client_fds/backend/node_modules/@fontsource/sora/LICENSE
splitter_client_fds/backend/node_modules/@fontsource/sora/README.md
splitter_client_fds/backend/node_modules/@fontsource/sora/index.css
splitter_client_fds/backend/node_modules/@fontsource/sora/latin-100.css
splitter_client_fds/backend/node_modules/@fontsource/sora/latin-200.css
splitter_client_fds/backend/node_modules/@fontsource/sora/latin-300.css
splitter_client_fds/backend/node_modules/@fontsource/sora/latin-400.css
splitter_client_fds/backend/node_modules/@fontsource/sora/latin-500.css
splitter_client_fds/backend/node_modules/@fontsource/sora/latin-600.css
splitter_client_fds/backend/node_modules/@fontsource/sora/latin-700.css
splitter_client_fds/backend/node_modules/@fontsource/sora/latin-800.css
splitter_client_fds/backend/node_modules/@fontsource/sora/latin-ext-100.css
splitter_client_fds/backend/node_modules/@fontsource/sora/latin-ext-200.css
splitter_client_fds/backend/node_modules/@fontsource/sora/latin-ext-300.css
splitter_client_fds/backend/node_modules/@fontsource/sora/latin-ext-400.css
splitter_client_fds-0.1.0.dist-info/METADATA
splitter_client_fds-0.1.0.dist-info/WHEEL
splitter_client_fds-0.1.0.dist-info/entry_points.txt
splitter_client_fds-0.1.0.dist-info/top_level.txt
splitter_client_fds-0.1.0.dist-info/RECORD
